dmcan/__init__.py
dmcan/dmcan.py
dmcan-0.1.3.5.dist-info/LICENSE
dmcan-0.1.3.5.dist-info/METADATA
dmcan-0.1.3.5.dist-info/WHEEL
dmcan-0.1.3.5.dist-info/top_level.txt
dmcan-0.1.3.5.dist-info/RECORD
